.bzrignore
.reahlproject
COPYING
LICENSE
reahl
setup.py
etc/reahl.config.py
etc/web.config.py
reahl/__init__.py
reahl/webelixirimpl.py
reahl/webelixirimpl_dev/__init__.py
reahl/webelixirimpl_dev/basic_tests.py
reahl_web_elixirimpl.egg-info/PKG-INFO
reahl_web_elixirimpl.egg-info/SOURCES.txt
reahl_web_elixirimpl.egg-info/dependency_links.txt
reahl_web_elixirimpl.egg-info/entry_points.txt
reahl_web_elixirimpl.egg-info/namespace_packages.txt
reahl_web_elixirimpl.egg-info/requires.txt
reahl_web_elixirimpl.egg-info/top_level.txt