Metadata-Version: 1.0
Name: reahl-web-elixirimpl
Version: 2.1.0
Summary: An implementation of Reahl persisted classes using Elixir.
Home-page: http://www.reahl.org
Author: Iwan Vosloo
Author-email: iwan@reahl.org
License: UNKNOWN
Platform: UNKNOWN
